greek_accentuation/__init__.py
greek_accentuation/accentuation.py
greek_accentuation/characters.py
greek_accentuation/syllabify.py
greek_accentuation-1.2.0.dist-info/DESCRIPTION.rst
greek_accentuation-1.2.0.dist-info/METADATA
greek_accentuation-1.2.0.dist-info/RECORD
greek_accentuation-1.2.0.dist-info/WHEEL
greek_accentuation-1.2.0.dist-info/metadata.json
greek_accentuation-1.2.0.dist-info/top_level.txt
