Metadata-Version: 2.0
Name: greek-accentuation
Version: 1.2.0
Summary: Python 3 library for accenting (and analyzing the accentuation of) Ancient Greek words
Home-page: http://github.com/jtauber/greek-accentuation
Author: James Tauber
Author-email: jtauber@jtauber.com
License: MIT
Platform: UNKNOWN
Classifier: Development Status :: 5 - Production/Stable
Classifier: License :: OSI Approved :: MIT License
Classifier: Programming Language :: Python :: 3.3
Classifier: Programming Language :: Python :: 3.4
Classifier: Programming Language :: Python :: 3.5
Classifier: Programming Language :: Python :: 3.6
Classifier: Topic :: Text Processing :: Linguistic
